.gitignore
LICENSE
README.md
setup.py
test.py
torch_unified_gpu.cpp
torch_unified/__init__.py
torch_unified.egg-info/PKG-INFO
torch_unified.egg-info/SOURCES.txt
torch_unified.egg-info/dependency_links.txt
torch_unified.egg-info/requires.txt
torch_unified.egg-info/top_level.txt