Metadata-Version: 2.1
Name: torch-unified
Version: 0.1
Summary: add support for unified CPU/CUDA memory to pytorch.
Home-page: https://github.com/siemanko/torch-unified
Author: Szymon Sidor
Author-email: szymon.szymon@gmail.com
License: Public Domain
Platform: UNKNOWN
License-File: LICENSE
